denstatbank/__init__.py
denstatbank/denstatbank.py
denstatbank/utils.py
tests/__init__.py
tests/mock_responses.py
tests/test_denstatbank.py
denstatbank-0.8.1.dist-info/LICENSE.txt
denstatbank-0.8.1.dist-info/METADATA
denstatbank-0.8.1.dist-info/WHEEL
denstatbank-0.8.1.dist-info/top_level.txt
denstatbank-0.8.1.dist-info/RECORD
