Metadata-Version: 2.1
Name: denstatbank
Version: 0.8.1
Summary: A Python API wrapper to Statistics Denmark's DataBank API
Author-email: Gopakumar Mohandas <gopakumarmohandas@gmail.com>
Project-URL: Homepage, https://github.com/gmohandas/denstatbank
Project-URL: Bug Tracker, https://github.com/gmohandas/denstatbank/issues
Classifier: Programming Language :: Python :: 3
Classifier: License :: OSI Approved :: MIT License
Classifier: Operating System :: OS Independent
Requires-Python: >=3.7
License-File: LICENSE.txt
Requires-Dist: pandas
Requires-Dist: pytest
Requires-Dist: requests
